operaciones/__init__.py
operaciones/modulo.py
operaciones-0.1.4.dist-info/METADATA
operaciones-0.1.4.dist-info/WHEEL
operaciones-0.1.4.dist-info/top_level.txt
operaciones-0.1.4.dist-info/RECORD
